hippycampus/__init__.py
hippycampus/__main__.py
hippycampus/cli.py
hippycampus/langchain_util.py
hippycampus/mcp_server.py
hippycampus/openapi_builder.py
hippycampus/spec_parser.py
mseep_hippycampus-0.1.3.dist-info/LICENSE.md
mseep_hippycampus-0.1.3.dist-info/METADATA
mseep_hippycampus-0.1.3.dist-info/WHEEL
mseep_hippycampus-0.1.3.dist-info/entry_points.txt
mseep_hippycampus-0.1.3.dist-info/RECORD
