Metadata-Version: 2.3
Name: mseep-hippycampus
Version: 0.1.3
Summary: 
Author: mseep
Author-email: support@skydeck.ai
Maintainer: mseep
Maintainer-email: support@skydeck.ai
Requires-Python: ==3.12.9
Classifier: Programming Language :: Python :: 3
Requires-Dist: httpx (>=0.28.1)
Requires-Dist: langchain (>=0.3.18,<0.4.0)
Requires-Dist: langchain-openai (>=0.3.6,<0.4.0)
Requires-Dist: mcp[cli] (>=1.3.0)
Requires-Dist: pydantic (>=2.10.6,<3.0.0)
Requires-Dist: requests (>=2.32.3,<3.0.0)
Requires-Dist: rich (>=13.9.4,<14.0.0)
